{
	"pages": [
		{
			"path": "pages/index/index",
			"style": {
				"navigationBarTitleText": "v-videos 播放器测试中心",
				"navigationBarBackgroundColor": "#0f1115",
				"navigationBarTextStyle": "white"
			}
		},
		{
			"path": "pages/demo-controls/demo-controls",
			"style": {
				"navigationBarTitleText": "控制条按键自由显隐配置",
				"navigationBarBackgroundColor": "#0f1115",
				"navigationBarTextStyle": "white"
			}
		},
		{
			"path": "pages/demo-episodes/demo-episodes",
			"style": {
				"navigationBarTitleText": "选集/剧集功能测试",
				"navigationBarBackgroundColor": "#0f1115",
				"navigationBarTextStyle": "white"
			}
		},
		{
			"path": "pages/demo-live/demo-live",
			"style": {
				"navigationBarTitleText": "直播源功能测试",
				"navigationBarBackgroundColor": "#0f1115",
				"navigationBarTextStyle": "white"
			}
		},
		{
			"path": "pages/demo-more/demo-more",
			"style": {
				"navigationBarTitleText": "更多操作面板测试",
				"navigationBarBackgroundColor": "#0f1115",
				"navigationBarTextStyle": "white"
			}
		},
		{
			"path": "pages/demo-rate/demo-rate",
			"style": {
				"navigationBarTitleText": "播放倍速切换测试",
				"navigationBarBackgroundColor": "#0f1115",
				"navigationBarTextStyle": "white"
			}
		},
		{
			"path": "pages/demo-loading/demo-loading",
			"style": {
				"navigationBarTitleText": "网络 Loading 状态测试",
				"navigationBarBackgroundColor": "#0f1115",
				"navigationBarTextStyle": "white"
			}
		}
	],
	"globalStyle": {
		"navigationBarTextStyle": "white",
		"navigationBarTitleText": "v-videos",
		"navigationBarBackgroundColor": "#0f1115",
		"backgroundColor": "#0f1115"
	}
}
